dm_pybloom-3.0.4.dist-info/DESCRIPTION.rst
dm_pybloom-3.0.4.dist-info/METADATA
dm_pybloom-3.0.4.dist-info/RECORD
dm_pybloom-3.0.4.dist-info/WHEEL
dm_pybloom-3.0.4.dist-info/metadata.json
dm_pybloom-3.0.4.dist-info/top_level.txt
dm_pybloom-3.0.4.dist-info/zip-safe
pybloom/__init__.py
pybloom/benchmarks.py
pybloom/pybloom.py
pybloom/tests.py
pybloom/utils.py
