Metadata-Version: 2.0
Name: dm-pybloom
Version: 3.0.4
Summary: Datamaran's fork of Pybloom adapted to Python3
Home-page: https://github.com/datamaranai/python-bloomfilter/
Author: jxub
Author-email: jjanarek@gmail.com
License: MIT
Keywords: data structures,bloom filter,bloom,filter,probabilistic,set
Platform: any
Classifier: License :: OSI Approved :: MIT License
Classifier: Programming Language :: Python
Classifier: Programming Language :: Python :: 3
Classifier: Programming Language :: Python :: 3.6
Classifier: Programming Language :: Python :: Implementation :: CPython
Classifier: Programming Language :: Python :: Implementation :: PyPy
Requires-Dist: bitarray (>=0.3.4)
